{
  "parent": "minecraft:item/generated",
  "textures": {
    "layer0": "moredelight:item/bread_slice"
  },
  "overrides": [
    {
      "predicate": {
        "eating": 1,
        "eat": 0.35
      },
      "model": "moredelight:item/bread_slice_eating_0"
    },
    {
      "predicate": {
        "eating": 1,
        "eat": 0.7
      },
      "model": "moredelight:item/bread_slice_eating_1"
    },
    {
      "predicate": {
        "eating": 1,
        "eat": 0.9
      },
      "model": "moredelight:item/bread_slice_eating_2"
    }
  ]
}